LICENSE.txt
README.md
setup.cfg
setup.py
lmppl/__init__.py
lmppl/ppl_encoder_decoder_lm.py
lmppl/ppl_mlm.py
lmppl/ppl_recurrent_lm.py
lmppl/util.py
lmppl.egg-info/PKG-INFO
lmppl.egg-info/SOURCES.txt
lmppl.egg-info/dependency_links.txt
lmppl.egg-info/requires.txt
lmppl.egg-info/top_level.txt
lmppl/lmppl_cl/__init__.py
test/test_analogy.py
test/test_model_with_simple_input.py