Metadata-Version: 2.1
Name: lmppl
Version: 0.1.9
Summary: Calculate perplexity on the text with pre-trained language models.
Home-page: https://github.com/asahi417/lmppl
Author: Asahi Ushio
Author-email: asahi1992ushio@gmail.com
License: MIT License
Download-URL: https://github.com/asahi417/lmppl/archive/v0.1.9.tar.gz
Keywords: language model,t5,gpt3,bert,perplexity,nlp
Platform: UNKNOWN
Classifier: Development Status :: 4 - Beta
Classifier: Intended Audience :: Developers
Classifier: Intended Audience :: Science/Research
Classifier: Topic :: Scientific/Engineering
Classifier: License :: OSI Approved :: MIT License
Classifier: Programming Language :: Python :: 3
Requires-Python: >=3.6
License-File: LICENSE.txt
